alicepackage/__init__.py
alicepackage/function.py
testalicepackage-0.1.0.dist-info/LICENSE
testalicepackage-0.1.0.dist-info/METADATA
testalicepackage-0.1.0.dist-info/WHEEL
testalicepackage-0.1.0.dist-info/top_level.txt
testalicepackage-0.1.0.dist-info/RECORD
